boudams/__init__.py
boudams/cli.py
boudams/encoder.py
boudams/tagger.py
boudams/trainer.py
boudams/utils.py
boudams/dataset/__init__.py
boudams/dataset/base.py
boudams/dataset/conllu.py
boudams/dataset/plaintext.py
boudams/model/__init__.py
boudams/model/base.py
boudams/model/bidir.py
boudams/model/conv.py
boudams/model/linear.py
boudams/model/lstm.py
boudams-0.1.2.dist-info/LICENSE
boudams-0.1.2.dist-info/METADATA
boudams-0.1.2.dist-info/WHEEL
boudams-0.1.2.dist-info/entry_points.txt
boudams-0.1.2.dist-info/top_level.txt
boudams-0.1.2.dist-info/RECORD
