Metadata-Version: 2.1
Name: boudams
Version: 0.1.2
Summary: A framework and toolkit for automatic segmentation
Home-page: https://github.com/ponteineptique/boudams
Author: Thibault Clérice
License: MIT
Platform: UNKNOWN
Classifier: License :: OSI Approved :: MIT License
Classifier: Programming Language :: Python
Classifier: Programming Language :: Python :: 3
Classifier: Programming Language :: Python :: 3.6
Classifier: Topic :: Text Processing :: Linguistic
Requires-Python: >=3.6.0
Requires-Dist: torch (>=1.0.1.post2)
Requires-Dist: tqdm (>=4.31.1)
Requires-Dist: unidecode (>=1.0.23)
Requires-Dist: leven (==1.0.4)
Requires-Dist: click (<=8.0,>=7.0)
Requires-Dist: regex (==2019.5.25)
Requires-Dist: mufidecode
Requires-Dist: matplotlib
Requires-Dist: sklearn
Requires-Dist: numpy
